mkdocs_copy_to_llm/__init__.py
mkdocs_copy_to_llm/exceptions.py
mkdocs_copy_to_llm/minify.py
mkdocs_copy_to_llm/plugin.py
mkdocs_copy_to_llm/py.typed
mkdocs_copy_to_llm/validation.py
mkdocs_copy_to_llm/assets/css/copy-to-llm.css
mkdocs_copy_to_llm/assets/js/copy-to-llm.js
mkdocs_copy_to_llm-0.2.8.dist-info/licenses/LICENSE
mkdocs_copy_to_llm-0.2.8.dist-info/METADATA
mkdocs_copy_to_llm-0.2.8.dist-info/WHEEL
mkdocs_copy_to_llm-0.2.8.dist-info/entry_points.txt
mkdocs_copy_to_llm-0.2.8.dist-info/top_level.txt
mkdocs_copy_to_llm-0.2.8.dist-info/RECORD
