Metadata-Version: 2.4
Name: mkdocs-copy-to-llm
Version: 0.2.8
Summary: MkDocs plugin to add 'Copy to LLM' buttons to documentation
Author-email: Leonardo Custodio <leonardo.custodio@parity.io>, David Castro <davidcastro@parity.io>, Karim Jedda  <karim@parity.io>
License-Expression: MIT
Project-URL: Homepage, https://github.com/leonardocustodio/mkdocs-copy-to-llm
Project-URL: Documentation, https://github.com/leonardocustodio/mkdocs-copy-to-llm#readme
Project-URL: Repository, https://github.com/leonardocustodio/mkdocs-copy-to-llm
Project-URL: Bug Tracker, https://github.com/leonardocustodio/mkdocs-copy-to-llm/issues
Project-URL: Changelog, https://github.com/leonardocustodio/mkdocs-copy-to-llm/releases
Keywords: mkdocs,plugin,documentation,llm,copy,ai,chatgpt,claude
Classifier: Development Status :: 5 - Production/Stable
Classifier: Intended Audience :: Developers
Classifier: Operating System :: OS Independent
Classifier: Programming Language :: Python :: 3
Classifier: Programming Language :: Python :: 3.9
Classifier: Programming Language :: Python :: 3.10
Classifier: Programming Language :: Python :: 3.11
Classifier: Programming Language :: Python :: 3.12
Classifier: Programming Language :: Python :: 3.13
Classifier: Topic :: Documentation
Classifier: Topic :: Text Processing
Classifier: Framework :: MkDocs
Requires-Python: >=3.9
License-File: LICENSE
Requires-Dist: mkdocs>=1.2
Provides-Extra: minify
Requires-Dist: jsmin>=3.0.0; extra == "minify"
Requires-Dist: csscompressor>=0.9.5; extra == "minify"
Provides-Extra: dev
Requires-Dist: pytest>=7.0; extra == "dev"
Requires-Dist: pytest-cov>=4.0; extra == "dev"
Requires-Dist: pytest-mock>=3.0; extra == "dev"
Requires-Dist: mypy>=1.0; extra == "dev"
Requires-Dist: ruff>=0.1.0; extra == "dev"
Requires-Dist: build>=0.10.0; extra == "dev"
Requires-Dist: twine>=4.0.0; extra == "dev"
Requires-Dist: mkdocs-material>=9.0; extra == "dev"
Requires-Dist: types-setuptools; extra == "dev"
Requires-Dist: jsmin>=3.0.0; extra == "dev"
Requires-Dist: csscompressor>=0.9.5; extra == "dev"
Requires-Dist: pre-commit>=3.0.0; extra == "dev"
Dynamic: license-file
